setup.cfg
setup.py
thumbor_head/__init__.py
thumbor_head/result_storage.py
thumbor_head.egg-info/PKG-INFO
thumbor_head.egg-info/SOURCES.txt
thumbor_head.egg-info/dependency_links.txt
thumbor_head.egg-info/requires.txt
thumbor_head.egg-info/top_level.txt