Metadata-Version: 1.0
Name: thumbor-head
Version: 0.1.1
Summary: Allow checking of http status code for all requests even if cached
Home-page: https://github.com/torsdag/thumbor_head
Author: Eric hermelin
Author-email: eric.hermelin@gmail.com
License: UNKNOWN
Keywords: thumbor,images,plugin
Platform: UNKNOWN
